fathah/TextClean.py
fathah/__init__.py
fathah/stopwords.py
fathah-0.0.2.dist-info/LICENSE
fathah-0.0.2.dist-info/METADATA
fathah-0.0.2.dist-info/WHEEL
fathah-0.0.2.dist-info/top_level.txt
fathah-0.0.2.dist-info/RECORD
