Metadata-Version: 2.1
Name: fathah
Version: 0.0.2
Summary: Lightweight NLP preprocessing package for Arabic language
Home-page: https://github.com/fathah/fathah_python
Author: Abdul Fathah KA
Author-email: fathah@ziqx.in
License: UNKNOWN
Keywords: nlp,fathah,arabic
Platform: UNKNOWN
Classifier: Programming Language :: Python :: 3
Classifier: License :: OSI Approved :: MIT License
Classifier: Operating System :: OS Independent
License-File: LICENSE
